multitenancy/__init__.py
multitenancy/multitenancy.py
multitenancy/commands/TenancyCreate.py
multitenancy/commands/TenancyDelete.py
multitenancy/commands/TenancyList.py
multitenancy/commands/TenancyMigrate.py
multitenancy/commands/TenancyMigrateRefresh.py
multitenancy/commands/TenancyMigrateReset.py
multitenancy/commands/TenancyMigrateRollback.py
multitenancy/commands/TenancyMigrateStatus.py
multitenancy/commands/TenancySeed.py
multitenancy/config/multitenancy.py
multitenancy/middlewares/tenant_finder_middleware.py
multitenancy/migrations/2022_07_07_230413_create_tenants_table.py
multitenancy/models/Tenant.py
multitenancy/providers/__init__.py
multitenancy/providers/multitenancy_provider.py
masonite_multitenancy-0.0.5.dist-info/LICENSE
masonite_multitenancy-0.0.5.dist-info/METADATA
masonite_multitenancy-0.0.5.dist-info/WHEEL
masonite_multitenancy-0.0.5.dist-info/top_level.txt
masonite_multitenancy-0.0.5.dist-info/RECORD
